tools_1c/__init__.py
tools_1c/rac.py
tools_1c/utils.py
tools_1c-0.1.1.dist-info/LICENSE
tools_1c-0.1.1.dist-info/METADATA
tools_1c-0.1.1.dist-info/WHEEL
tools_1c-0.1.1.dist-info/top_level.txt
tools_1c-0.1.1.dist-info/RECORD
