Metadata-Version: 2.1
Name: tools-1c
Version: 0.1.1
Summary: Tools for 1C:Enterprise
Home-page: https://github.com/qwedfgr/tools_1c
Author: George Kvelidze
Author-email: georgiykvelidze@gmail.com
License: MIT license
Keywords: tools_1c
Platform: UNKNOWN
Classifier: Development Status :: 2 - Pre-Alpha
Classifier: Intended Audience :: Developers
Classifier: License :: OSI Approved :: MIT License
Classifier: Natural Language :: English
Classifier: Programming Language :: Python :: 3.7
Classifier: Programming Language :: Python :: 3.8
Requires-Python: >=3.7
Requires-Dist: PyYAML
